not_a_virus/__init__.py
really_banned_package/__init__.py
really_banned_package-1.0.dist-info/METADATA
really_banned_package-1.0.dist-info/WHEEL
really_banned_package-1.0.dist-info/entry_points.txt
really_banned_package-1.0.dist-info/top_level.txt
really_banned_package-1.0.dist-info/RECORD
